{
  "lookup": {
    "rules": {
      "[{\"prev_action\": {\"action_name\": \"action_listen\"}, \"user\": {\"intent\": \"new_addy\"}}]": "direction2_form",
      "[{\"prev_action\": {\"action_name\": \"action_listen\"}, \"user\": {\"intent\": \"new_addy\"}}, {\"active_loop\": {\"name\": \"direction2_form\"}, \"prev_action\": {\"action_name\": \"direction2_form\"}, \"user\": {\"intent\": \"new_addy\"}}]": "action_listen",
      "[{\"prev_action\": {\"action_name\": \"action_listen\"}, \"user\": {\"intent\": \"user_name\"}}]": "utter_nice_2meet",
      "[{\"prev_action\": {\"action_name\": \"action_listen\"}, \"user\": {\"intent\": \"user_name\"}}, {\"prev_action\": {\"action_name\": \"utter_nice_2meet\"}, \"user\": {\"intent\": \"user_name\"}}]": "action_listen",
      "[{\"prev_action\": {\"action_name\": \"action_listen\"}, \"user\": {\"intent\": \"hotel_restr\"}}]": "rest_form",
      "[{\"prev_action\": {\"action_name\": \"action_listen\"}, \"user\": {\"intent\": \"hotel_restr\"}}, {\"active_loop\": {\"name\": \"rest_form\"}, \"prev_action\": {\"action_name\": \"rest_form\"}, \"user\": {\"intent\": \"hotel_restr\"}}]": "action_listen",
      "[{\"prev_action\": {\"action_name\": \"action_listen\"}, \"user\": {\"intent\": \"out_of_scope\"}}]": "utter_out_of_scope",
      "[{\"prev_action\": {\"action_name\": \"action_listen\"}, \"user\": {\"intent\": \"out_of_scope\"}}, {\"prev_action\": {\"action_name\": \"utter_out_of_scope\"}, \"user\": {\"intent\": \"out_of_scope\"}}]": "action_listen",
      "[{\"active_loop\": {\"name\": \"should_not_be_set\"}, \"prev_action\": {\"action_name\": \"hotel_form\"}}]": "action_hotelForm",
      "[{\"active_loop\": {\"name\": \"should_not_be_set\"}, \"prev_action\": {\"action_name\": \"hotel_form\"}}, {\"active_loop\": {\"name\": \"should_not_be_set\"}, \"prev_action\": {\"action_name\": \"action_hotelForm\"}}]": "action_listen",
      "[{\"prev_action\": {\"action_name\": \"action_listen\"}, \"user\": {\"intent\": \"hot_rest\"}}]": "direction1_form",
      "[{\"prev_action\": {\"action_name\": \"action_listen\"}, \"user\": {\"intent\": \"hot_rest\"}}, {\"active_loop\": {\"name\": \"direction1_form\"}, \"prev_action\": {\"action_name\": \"direction1_form\"}, \"user\": {\"intent\": \"hot_rest\"}}]": "action_listen",
      "[{\"prev_action\": {\"action_name\": \"action_listen\"}, \"user\": {\"intent\": \"hotel_book\"}}]": "hotel_form",
      "[{\"prev_action\": {\"action_name\": \"action_listen\"}, \"user\": {\"intent\": \"hotel_book\"}}, {\"active_loop\": {\"name\": \"hotel_form\"}, \"prev_action\": {\"action_name\": \"hotel_form\"}, \"user\": {\"intent\": \"hotel_book\"}}]": "action_listen",
      "[{\"active_loop\": {\"name\": \"should_not_be_set\"}, \"prev_action\": {\"action_name\": \"rest_form\"}}]": "action_rest_form",
      "[{\"active_loop\": {\"name\": \"should_not_be_set\"}, \"prev_action\": {\"action_name\": \"rest_form\"}}, {\"active_loop\": {\"name\": \"should_not_be_set\"}, \"prev_action\": {\"action_name\": \"action_rest_form\"}}]": "action_listen",
      "[{\"active_loop\": {\"name\": \"should_not_be_set\"}, \"prev_action\": {\"action_name\": \"direction1_form\"}}]": "action_direction1_form",
      "[{\"active_loop\": {\"name\": \"should_not_be_set\"}, \"prev_action\": {\"action_name\": \"direction1_form\"}}, {\"active_loop\": {\"name\": \"should_not_be_set\"}, \"prev_action\": {\"action_name\": \"action_direction1_form\"}}]": "action_listen",
      "[{\"prev_action\": {\"action_name\": \"action_listen\"}, \"user\": {\"intent\": \"thanks\"}}]": "utter_welcome",
      "[{\"prev_action\": {\"action_name\": \"action_listen\"}, \"user\": {\"intent\": \"thanks\"}}, {\"prev_action\": {\"action_name\": \"utter_welcome\"}, \"user\": {\"intent\": \"thanks\"}}]": "utter_furtherHelp",
      "[{\"prev_action\": {\"action_name\": \"action_listen\"}, \"user\": {\"intent\": \"thanks\"}}, {\"prev_action\": {\"action_name\": \"utter_welcome\"}, \"user\": {\"intent\": \"thanks\"}}, {\"prev_action\": {\"action_name\": \"utter_furtherHelp\"}, \"user\": {\"intent\": \"thanks\"}}]": "action_listen",
      "[{\"active_loop\": {\"name\": \"should_not_be_set\"}, \"prev_action\": {\"action_name\": \"direction2_form\"}}]": "action_direction2_form",
      "[{\"active_loop\": {\"name\": \"should_not_be_set\"}, \"prev_action\": {\"action_name\": \"direction2_form\"}}, {\"active_loop\": {\"name\": \"should_not_be_set\"}, \"prev_action\": {\"action_name\": \"action_direction2_form\"}}]": "action_listen",
      "[{\"prev_action\": {\"action_name\": \"action_listen\"}, \"user\": {\"intent\": \"goodbye\"}}]": "utter_goodbye",
      "[{\"prev_action\": {\"action_name\": \"action_listen\"}, \"user\": {\"intent\": \"goodbye\"}}, {\"prev_action\": {\"action_name\": \"utter_goodbye\"}, \"user\": {\"intent\": \"goodbye\"}}]": "action_chat_restart",
      "[{\"prev_action\": {\"action_name\": \"action_listen\"}, \"user\": {\"intent\": \"goodbye\"}}, {\"prev_action\": {\"action_name\": \"utter_goodbye\"}, \"user\": {\"intent\": \"goodbye\"}}, {\"prev_action\": {\"action_name\": \"action_chat_restart\"}, \"user\": {\"intent\": \"goodbye\"}}]": "action_listen"
    },
    "rule_only_slots": [],
    "rule_only_loops": [],
    "rules_for_loop_unhappy_path": {
      "[{\"prev_action\": {\"action_name\": \"action_listen\"}}, {\"active_loop\": {\"name\": \"direction2_form\"}, \"prev_action\": {\"action_name\": \"direction2_form\"}, \"user\": {\"intent\": \"new_addy\"}}]": "do_not_predict_loop_action",
      "[{\"prev_action\": {\"action_name\": \"action_listen\"}}, {\"active_loop\": {\"name\": \"rest_form\"}, \"prev_action\": {\"action_name\": \"rest_form\"}, \"user\": {\"intent\": \"hotel_restr\"}}]": "do_not_predict_loop_action",
      "[{\"prev_action\": {\"action_name\": \"action_listen\"}}, {\"active_loop\": {\"name\": \"direction1_form\"}, \"prev_action\": {\"action_name\": \"direction1_form\"}, \"user\": {\"intent\": \"hot_rest\"}}]": "do_not_predict_loop_action",
      "[{\"prev_action\": {\"action_name\": \"action_listen\"}}, {\"active_loop\": {\"name\": \"hotel_form\"}, \"prev_action\": {\"action_name\": \"hotel_form\"}, \"user\": {\"intent\": \"hotel_book\"}}]": "do_not_predict_loop_action",
      "[{\"prev_action\": {\"action_name\": \"action_listen\"}}, {\"active_loop\": {\"name\": \"rest_form\"}, \"prev_action\": {\"action_name\": \"utter_out_of_scope\"}, \"user\": {\"intent\": \"out_of_scope\"}}]": "do_not_predict_loop_action",
      "[{\"prev_action\": {\"action_name\": \"utter_out_of_scope\"}}, {\"active_loop\": {\"name\": \"rest_form\"}, \"prev_action\": {\"action_name\": \"utter_ask_continue\"}, \"user\": {\"intent\": \"out_of_scope\"}}]": "do_not_predict_loop_action",
      "[{\"prev_action\": {\"action_name\": \"utter_ask_continue\"}}, {\"active_loop\": {\"name\": \"rest_form\"}, \"prev_action\": {\"action_name\": \"action_listen\"}, \"user\": {\"intent\": \"affirm\"}}]": "loop_was_interrupted",
      "[{\"prev_action\": {\"action_name\": \"action_listen\"}}, {\"active_loop\": {\"name\": \"hotel_form\"}, \"prev_action\": {\"action_name\": \"utter_out_of_scope\"}, \"user\": {\"intent\": \"out_of_scope\"}}]": "do_not_predict_loop_action",
      "[{\"prev_action\": {\"action_name\": \"utter_out_of_scope\"}}, {\"active_loop\": {\"name\": \"hotel_form\"}, \"prev_action\": {\"action_name\": \"utter_ask_continue\"}, \"user\": {\"intent\": \"out_of_scope\"}}]": "do_not_predict_loop_action",
      "[{\"prev_action\": {\"action_name\": \"action_listen\"}}, {\"active_loop\": {\"name\": \"hotel_form\"}, \"prev_action\": {\"action_name\": \"utter_furtherHelp\"}, \"user\": {\"intent\": \"deny\"}}]": "do_not_predict_loop_action",
      "[{\"prev_action\": {\"action_name\": \"action_listen\"}}, {\"active_loop\": {\"name\": \"rest_form\"}, \"prev_action\": {\"action_name\": \"utter_furtherHelp\"}, \"user\": {\"intent\": \"deny\"}}]": "do_not_predict_loop_action",
      "[{\"prev_action\": {\"action_name\": \"action_listen\"}}, {\"active_loop\": {\"name\": \"direction1_form\"}, \"prev_action\": {\"action_name\": \"utter_out_of_scope\"}, \"user\": {\"intent\": \"out_of_scope\"}}]": "do_not_predict_loop_action",
      "[{\"prev_action\": {\"action_name\": \"utter_out_of_scope\"}}, {\"active_loop\": {\"name\": \"direction1_form\"}, \"prev_action\": {\"action_name\": \"utter_ask_continue\"}, \"user\": {\"intent\": \"out_of_scope\"}}]": "do_not_predict_loop_action",
      "[{\"prev_action\": {\"action_name\": \"action_listen\"}}, {\"active_loop\": {\"name\": \"direction1_form\"}, \"prev_action\": {\"action_name\": \"utter_furtherHelp\"}, \"user\": {\"intent\": \"deny\"}}]": "do_not_predict_loop_action",
      "[{\"prev_action\": {\"action_name\": \"action_listen\"}}, {\"active_loop\": {\"name\": \"direction2_form\"}, \"prev_action\": {\"action_name\": \"utter_out_of_scope\"}, \"user\": {\"intent\": \"out_of_scope\"}}]": "do_not_predict_loop_action",
      "[{\"prev_action\": {\"action_name\": \"utter_out_of_scope\"}}, {\"active_loop\": {\"name\": \"direction2_form\"}, \"prev_action\": {\"action_name\": \"utter_ask_continue\"}, \"user\": {\"intent\": \"out_of_scope\"}}]": "do_not_predict_loop_action",
      "[{\"prev_action\": {\"action_name\": \"utter_ask_continue\"}}, {\"active_loop\": {\"name\": \"direction2_form\"}, \"prev_action\": {\"action_name\": \"action_listen\"}, \"user\": {\"intent\": \"affirm\"}}]": "loop_was_interrupted",
      "[{\"prev_action\": {\"action_name\": \"action_listen\"}}, {\"active_loop\": {\"name\": \"direction2_form\"}, \"prev_action\": {\"action_name\": \"utter_furtherHelp\"}, \"user\": {\"intent\": \"deny\"}}]": "do_not_predict_loop_action",
      "[{\"prev_action\": {\"action_name\": \"utter_ask_continue\"}}, {\"active_loop\": {\"name\": \"direction1_form\"}, \"prev_action\": {\"action_name\": \"action_listen\"}, \"user\": {\"intent\": \"affirm\"}}]": "loop_was_interrupted",
      "[{\"prev_action\": {\"action_name\": \"utter_ask_continue\"}}, {\"active_loop\": {\"name\": \"hotel_form\"}, \"prev_action\": {\"action_name\": \"action_listen\"}, \"user\": {\"intent\": \"affirm\"}}]": "loop_was_interrupted"
    },
    "rules_not_in_stories": [
      "handling active loops and forms - rest_form",
      "handling active loops and forms - direction1_form",
      "handling active loops and forms - direction2_form",
      "handling active loops and forms - hotel_form",
      "[{\"prev_action\": {\"action_name\": \"action_listen\"}, \"user\": {\"intent\": \"thanks\"}}]",
      "[{\"prev_action\": {\"action_name\": \"action_listen\"}, \"user\": {\"intent\": \"goodbye\"}}, {\"prev_action\": {\"action_name\": \"utter_goodbye\"}, \"user\": {\"intent\": \"goodbye\"}}, {\"prev_action\": {\"action_name\": \"action_chat_restart\"}, \"user\": {\"intent\": \"goodbye\"}}]",
      "[{\"prev_action\": {\"action_name\": \"action_listen\"}, \"user\": {\"intent\": \"goodbye\"}}]",
      "[{\"prev_action\": {\"action_name\": \"action_listen\"}, \"user\": {\"intent\": \"thanks\"}}, {\"prev_action\": {\"action_name\": \"utter_welcome\"}, \"user\": {\"intent\": \"thanks\"}}]",
      "predicting default action with intent restart",
      "[{\"prev_action\": {\"action_name\": \"action_listen\"}, \"user\": {\"intent\": \"thanks\"}}, {\"prev_action\": {\"action_name\": \"utter_welcome\"}, \"user\": {\"intent\": \"thanks\"}}, {\"prev_action\": {\"action_name\": \"utter_furtherHelp\"}, \"user\": {\"intent\": \"thanks\"}}]",
      "[{\"prev_action\": {\"action_name\": \"action_listen\"}, \"user\": {\"intent\": \"goodbye\"}}, {\"prev_action\": {\"action_name\": \"utter_goodbye\"}, \"user\": {\"intent\": \"goodbye\"}}]",
      "[{\"prev_action\": {\"action_name\": \"action_listen\"}, \"user\": {\"intent\": \"out_of_scope\"}}, {\"prev_action\": {\"action_name\": \"utter_out_of_scope\"}, \"user\": {\"intent\": \"out_of_scope\"}}]",
      "predicting default action with intent back",
      "predicting default action with intent session_start"
    ]
  }
}